{
  "date": "2026-05-19",
  "fetched_at": "03:35 PM IST",
  "open_positions": 59,
  "hit_count": 2,
  "probable_count": 0,
  "exit_due_count": 7,
  "fetch_failed": [],
  "results": [
    {
      "symbol": "COCHINSHIP.NS",
      "signal": "UP_TRI",
      "signal_date": "2026-04-17",
      "direction": "LONG",
      "entry": 1498.1,
      "stop": 1123.26,
      "open": 1516.0,
      "close": 1489.6,
      "high": 1531.0,
      "low": 1484.1,
      "stop_hit": false,
      "stop_probable": false,
      "stop_status": "SAFE",
      "note": "Close \u20b91489.60 | Stop \u20b91123.26 | P&L -0.02R",
      "pnl_pct": -0.57,
      "pnl_r": -0.02,
      "exit_due": false,
      "day_number": 6,
      "fetch_time": "03:35 PM IST"
    },
    {
      "symbol": "GRSE.NS",
      "signal": "UP_TRI",
      "signal_date": "2026-04-17",
      "direction": "LONG",
      "entry": 2607.8,
      "stop": 1845.96,
      "open": 2595.0,
      "close": 2658.5,
      "high": 2685.0,
      "low": 2595.0,
      "stop_hit": false,
      "stop_probable": false,
      "stop_status": "SAFE",
      "note": "Close \u20b92658.50 | Stop \u20b91845.96 | P&L +0.07R",
      "pnl_pct": 1.94,
      "pnl_r": 0.07,
      "exit_due": false,
      "day_number": 6,
      "fetch_time": "03:35 PM IST"
    },
    {
      "symbol": "YESBANK.NS",
      "signal": "UP_TRI",
      "signal_date": "2026-04-17",
      "direction": "LONG",
      "entry": 19.95,
      "stop": 16.6,
      "open": 21.84,
      "close": 21.97,
      "high": 22.13,
      "low": 21.72,
      "stop_hit": false,
      "stop_probable": false,
      "stop_status": "SAFE",
      "note": "Close \u20b921.97 | Stop \u20b916.60 | P&L +0.60R",
      "pnl_pct": 10.13,
      "pnl_r": 0.6,
      "exit_due": false,
      "day_number": 6,
      "fetch_time": "03:35 PM IST"
    },
    {
      "symbol": "COLPAL.NS",
      "signal": "UP_TRI",
      "signal_date": "2026-04-17",
      "direction": "LONG",
      "entry": 1977.4,
      "stop": 1725.16,
      "open": 2152.0,
      "close": 2188.3,
      "high": 2223.7,
      "low": 2152.0,
      "stop_hit": false,
      "stop_probable": false,
      "stop_status": "SAFE",
      "note": "Close \u20b92188.30 | Stop \u20b91725.16 | P&L +0.84R",
      "pnl_pct": 10.67,
      "pnl_r": 0.84,
      "exit_due": false,
      "day_number": 6,
      "fetch_time": "03:35 PM IST"
    },
    {
      "symbol": "NYKAA.NS",
      "signal": "UP_TRI",
      "signal_date": "2026-04-17",
      "direction": "LONG",
      "entry": 262.61,
      "stop": 224.18,
      "open": 274.95,
      "close": 271.45,
      "high": 275.2,
      "low": 270.0,
      "stop_hit": false,
      "stop_probable": false,
      "stop_status": "SAFE",
      "note": "Close \u20b9271.45 | Stop \u20b9224.18 | P&L +0.23R",
      "pnl_pct": 3.37,
      "pnl_r": 0.23,
      "exit_due": false,
      "day_number": 6,
      "fetch_time": "03:35 PM IST"
    },
    {
      "symbol": "RVNL.NS",
      "signal": "UP_TRI",
      "signal_date": "2026-04-17",
      "direction": "LONG",
      "entry": 293.89,
      "stop": 235.84,
      "open": 276.85,
      "close": 271.55,
      "high": 278.3,
      "low": 270.35,
      "stop_hit": false,
      "stop_probable": false,
      "stop_status": "SAFE",
      "note": "Close \u20b9271.55 | Stop \u20b9235.84 | P&L -0.38R",
      "pnl_pct": -7.6,
      "pnl_r": -0.38,
      "exit_due": false,
      "day_number": 6,
      "fetch_time": "03:35 PM IST"
    },
    {
      "symbol": "SUMICHEM.NS",
      "signal": "UP_TRI",
      "signal_date": "2026-04-17",
      "direction": "LONG",
      "entry": 423.4,
      "stop": 348.52,
      "open": 453.95,
      "close": 468.9,
      "high": 474.8,
      "low": 450.05,
      "stop_hit": false,
      "stop_probable": false,
      "stop_status": "SAFE",
      "note": "Close \u20b9468.90 | Stop \u20b9348.52 | P&L +0.61R",
      "pnl_pct": 10.75,
      "pnl_r": 0.61,
      "exit_due": false,
      "day_number": 6,
      "fetch_time": "03:35 PM IST"
    },
    {
      "symbol": "GNFC.NS",
      "signal": "UP_TRI",
      "signal_date": "2026-04-17",
      "direction": "LONG",
      "entry": 463.05,
      "stop": 349.05,
      "open": 532.9,
      "close": 545.95,
      "high": 552.0,
      "low": 526.0,
      "stop_hit": false,
      "stop_probable": false,
      "stop_status": "SAFE",
      "note": "Close \u20b9545.95 | Stop \u20b9349.05 | P&L +0.73R",
      "pnl_pct": 17.9,
      "pnl_r": 0.73,
      "exit_due": false,
      "day_number": 6,
      "fetch_time": "03:35 PM IST"
    },
    {
      "symbol": "AUBANK.NS",
      "signal": "UP_TRI",
      "signal_date": "2026-04-21",
      "direction": "LONG",
      "entry": 997.65,
      "stop": 793.65,
      "open": 980.0,
      "close": 971.9,
      "high": 982.9,
      "low": 968.6,
      "stop_hit": false,
      "stop_probable": false,
      "stop_status": "SAFE",
      "note": "Close \u20b9971.90 | Stop \u20b9793.65 | P&L -0.13R",
      "pnl_pct": -2.58,
      "pnl_r": -0.13,
      "exit_due": false,
      "day_number": 6,
      "fetch_time": "03:35 PM IST"
    },
    {
      "symbol": "SBILIFE.NS",
      "signal": "UP_TRI",
      "signal_date": "2026-04-21",
      "direction": "LONG",
      "entry": 1982.5,
      "stop": 1673.31,
      "open": 1846.0,
      "close": 1881.4,
      "high": 1892.0,
      "low": 1845.4,
      "stop_hit": false,
      "stop_probable": false,
      "stop_status": "SAFE",
      "note": "Close \u20b91881.40 | Stop \u20b91673.31 | P&L -0.33R",
      "pnl_pct": -5.1,
      "pnl_r": -0.33,
      "exit_due": false,
      "day_number": 6,
      "fetch_time": "03:35 PM IST"
    },
    {
      "symbol": "HINDUNILVR.NS",
      "signal": "UP_TRI",
      "signal_date": "2026-04-21",
      "direction": "LONG",
      "entry": 2231.5,
      "stop": 1968.62,
      "open": 2242.0,
      "close": 2232.9,
      "high": 2282.0,
      "low": 2229.5,
      "stop_hit": false,
      "stop_probable": false,
      "stop_status": "SAFE",
      "note": "Close \u20b92232.90 | Stop \u20b91968.62 | P&L +0.01R",
      "pnl_pct": 0.06,
      "pnl_r": 0.01,
      "exit_due": false,
      "day_number": 6,
      "fetch_time": "03:35 PM IST"
    },
    {
      "symbol": "KEC.NS",
      "signal": "UP_TRI",
      "signal_date": "2026-04-21",
      "direction": "LONG",
      "entry": 559.55,
      "stop": 474.7,
      "open": 490.4,
      "close": 469.4,
      "high": 495.0,
      "low": 466.0,
      "stop_hit": true,
      "stop_probable": true,
      "stop_status": "HIT",
      "note": "Intraday low \u20b9466.00 hit stop \u20b9474.70 \u2014 exit confirmed",
      "pnl_pct": -16.11,
      "pnl_r": -1.06,
      "exit_due": false,
      "day_number": 6,
      "fetch_time": "03:35 PM IST"
    },
    {
      "symbol": "FORTIS.NS",
      "signal": "UP_TRI",
      "signal_date": "2026-04-21",
      "direction": "LONG",
      "entry": 890.9,
      "stop": 739.26,
      "open": 962.15,
      "close": 960.55,
      "high": 975.0,
      "low": 955.5,
      "stop_hit": false,
      "stop_probable": false,
      "stop_status": "SAFE",
      "note": "Close \u20b9960.55 | Stop \u20b9739.26 | P&L +0.46R",
      "pnl_pct": 7.82,
      "pnl_r": 0.46,
      "exit_due": false,
      "day_number": 6,
      "fetch_time": "03:35 PM IST"
    },
    {
      "symbol": "AARTIIND.NS",
      "signal": "UP_TRI",
      "signal_date": "2026-04-22",
      "direction": "LONG",
      "entry": 451.2,
      "stop": 376.33,
      "open": 460.0,
      "close": 469.25,
      "high": 471.6,
      "low": 458.0,
      "stop_hit": false,
      "stop_probable": false,
      "stop_status": "SAFE",
      "note": "Close \u20b9469.25 | Stop \u20b9376.33 | P&L +0.24R",
      "pnl_pct": 4.0,
      "pnl_r": 0.24,
      "exit_due": false,
      "day_number": 6,
      "fetch_time": "03:35 PM IST"
    },
    {
      "symbol": "INFY.NS",
      "signal": "DOWN_TRI",
      "signal_date": "2026-04-24",
      "direction": "SHORT",
      "entry": 1240.6,
      "stop": 1416.75,
      "open": 1162.0,
      "close": 1196.9,
      "high": 1198.4,
      "low": 1162.0,
      "stop_hit": false,
      "stop_probable": false,
      "stop_status": "SAFE",
      "note": "Close \u20b91196.90 | Stop \u20b91416.75 | P&L +0.25R",
      "pnl_pct": 3.52,
      "pnl_r": 0.25,
      "exit_due": false,
      "day_number": 6,
      "fetch_time": "03:35 PM IST"
    },
    {
      "symbol": "COALINDIA.NS",
      "signal": "UP_TRI",
      "signal_date": "2026-04-28",
      "direction": "LONG",
      "entry": 452.5,
      "stop": 411.8,
      "open": 462.1,
      "close": 456.95,
      "high": 463.25,
      "low": 454.0,
      "stop_hit": false,
      "stop_probable": false,
      "stop_status": "SAFE",
      "note": "Close \u20b9456.95 | Stop \u20b9411.80 | P&L +0.11R",
      "pnl_pct": 0.98,
      "pnl_r": 0.11,
      "exit_due": false,
      "day_number": 6,
      "fetch_time": "03:35 PM IST"
    },
    {
      "symbol": "BAJAJ-AUTO.NS",
      "signal": "DOWN_TRI",
      "signal_date": "2026-04-30",
      "direction": "SHORT",
      "entry": 9543.5,
      "stop": 10247.78,
      "open": 10198.5,
      "close": 10205.0,
      "high": 10285.0,
      "low": 10143.0,
      "stop_hit": true,
      "stop_probable": true,
      "stop_status": "HIT",
      "note": "Intraday high \u20b910285.00 hit stop \u20b910247.78 \u2014 exit confirmed",
      "pnl_pct": -6.93,
      "pnl_r": -0.94,
      "exit_due": false,
      "day_number": 6,
      "fetch_time": "03:35 PM IST"
    },
    {
      "symbol": "APLAPOLLO.NS",
      "signal": "DOWN_TRI",
      "signal_date": "2026-05-07",
      "direction": "SHORT",
      "entry": 1914.7,
      "stop": 2247.29,
      "open": 1882.0,
      "close": 1864.5,
      "high": 1888.9,
      "low": 1853.6,
      "stop_hit": false,
      "stop_probable": false,
      "stop_status": "SAFE",
      "note": "Close \u20b91864.50 | Stop \u20b92247.29 | P&L +0.15R",
      "pnl_pct": 2.62,
      "pnl_r": 0.15,
      "exit_due": false,
      "day_number": 6,
      "fetch_time": "03:35 PM IST"
    },
    {
      "symbol": "RBLBANK.NS",
      "signal": "UP_TRI",
      "signal_date": "2026-05-12",
      "direction": "LONG",
      "entry": 337.5,
      "stop": 295.96,
      "open": 327.4,
      "close": 323.65,
      "high": 332.15,
      "low": 322.55,
      "stop_hit": false,
      "stop_probable": false,
      "stop_status": "SAFE",
      "note": "Close \u20b9323.65 | Stop \u20b9295.96 | P&L -0.33R",
      "pnl_pct": -4.1,
      "pnl_r": -0.33,
      "exit_due": true,
      "day_number": 6,
      "fetch_time": "03:35 PM IST"
    },
    {
      "symbol": "NATIONALUM.NS",
      "signal": "DOWN_TRI",
      "signal_date": "2026-05-12",
      "direction": "SHORT",
      "entry": 393.05,
      "stop": 458.39,
      "open": 402.0,
      "close": 398.95,
      "high": 403.5,
      "low": 391.45,
      "stop_hit": false,
      "stop_probable": false,
      "stop_status": "SAFE",
      "note": "Close \u20b9398.95 | Stop \u20b9458.39 | P&L -0.09R",
      "pnl_pct": -1.5,
      "pnl_r": -0.09,
      "exit_due": true,
      "day_number": 6,
      "fetch_time": "03:35 PM IST"
    },
    {
      "symbol": "POWERGRID.NS",
      "signal": "DOWN_TRI",
      "signal_date": "2026-05-12",
      "direction": "SHORT",
      "entry": 310.9,
      "stop": 331.73,
      "open": 296.6,
      "close": 298.6,
      "high": 300.0,
      "low": 294.55,
      "stop_hit": false,
      "stop_probable": false,
      "stop_status": "SAFE",
      "note": "Close \u20b9298.60 | Stop \u20b9331.73 | P&L +0.59R",
      "pnl_pct": 3.96,
      "pnl_r": 0.59,
      "exit_due": true,
      "day_number": 6,
      "fetch_time": "03:35 PM IST"
    },
    {
      "symbol": "NTPC.NS",
      "signal": "DOWN_TRI",
      "signal_date": "2026-05-12",
      "direction": "SHORT",
      "entry": 392.95,
      "stop": 423.89,
      "open": 386.7,
      "close": 389.4,
      "high": 392.75,
      "low": 386.05,
      "stop_hit": false,
      "stop_probable": false,
      "stop_status": "SAFE",
      "note": "Close \u20b9389.40 | Stop \u20b9423.89 | P&L +0.11R",
      "pnl_pct": 0.9,
      "pnl_r": 0.11,
      "exit_due": true,
      "day_number": 6,
      "fetch_time": "03:35 PM IST"
    },
    {
      "symbol": "AMBUJACEM.NS",
      "signal": "DOWN_TRI",
      "signal_date": "2026-05-12",
      "direction": "SHORT",
      "entry": 436.2,
      "stop": 483.06,
      "open": 430.5,
      "close": 431.7,
      "high": 434.6,
      "low": 428.8,
      "stop_hit": false,
      "stop_probable": false,
      "stop_status": "SAFE",
      "note": "Close \u20b9431.70 | Stop \u20b9483.06 | P&L +0.10R",
      "pnl_pct": 1.03,
      "pnl_r": 0.1,
      "exit_due": true,
      "day_number": 6,
      "fetch_time": "03:35 PM IST"
    },
    {
      "symbol": "ACC.NS",
      "signal": "DOWN_TRI",
      "signal_date": "2026-05-12",
      "direction": "SHORT",
      "entry": 1357.9,
      "stop": 1496.37,
      "open": 1367.5,
      "close": 1359.3,
      "high": 1373.1,
      "low": 1353.3,
      "stop_hit": false,
      "stop_probable": false,
      "stop_status": "SAFE",
      "note": "Close \u20b91359.30 | Stop \u20b91496.37 | P&L -0.01R",
      "pnl_pct": -0.1,
      "pnl_r": -0.01,
      "exit_due": true,
      "day_number": 6,
      "fetch_time": "03:35 PM IST"
    },
    {
      "symbol": "TORNTPOWER.NS",
      "signal": "DOWN_TRI",
      "signal_date": "2026-05-12",
      "direction": "SHORT",
      "entry": 1680.9,
      "stop": 1890.96,
      "open": 1533.5,
      "close": 1480.3,
      "high": 1543.9,
      "low": 1475.0,
      "stop_hit": false,
      "stop_probable": false,
      "stop_status": "SAFE",
      "note": "Close \u20b91480.30 | Stop \u20b91890.96 | P&L +0.95R",
      "pnl_pct": 11.93,
      "pnl_r": 0.95,
      "exit_due": true,
      "day_number": 6,
      "fetch_time": "03:35 PM IST"
    },
    {
      "symbol": "MARUTI.NS",
      "signal": "UP_TRI",
      "signal_date": "2026-05-13",
      "direction": "LONG",
      "entry": 13172.0,
      "stop": 12500.91,
      "open": 13034.0,
      "close": 12956.0,
      "high": 13104.0,
      "low": 12900.0,
      "stop_hit": false,
      "stop_probable": false,
      "stop_status": "SAFE",
      "note": "Close \u20b912956.00 | Stop \u20b912500.91 | P&L -0.32R",
      "pnl_pct": -1.64,
      "pnl_r": -0.32,
      "exit_due": false,
      "day_number": 5,
      "fetch_time": "03:35 PM IST"
    },
    {
      "symbol": "JSWSTEEL.NS",
      "signal": "DOWN_TRI",
      "signal_date": "2026-05-13",
      "direction": "SHORT",
      "entry": 1252.3,
      "stop": 1338.41,
      "open": 1298.0,
      "close": 1285.2,
      "high": 1299.7,
      "low": 1282.7,
      "stop_hit": false,
      "stop_probable": false,
      "stop_status": "SAFE",
      "note": "Close \u20b91285.20 | Stop \u20b91338.41 | P&L -0.38R",
      "pnl_pct": -2.63,
      "pnl_r": -0.38,
      "exit_due": false,
      "day_number": 5,
      "fetch_time": "03:35 PM IST"
    },
    {
      "symbol": "TATAPOWER.NS",
      "signal": "DOWN_TRI",
      "signal_date": "2026-05-13",
      "direction": "SHORT",
      "entry": 418.4,
      "stop": 477.12,
      "open": 404.3,
      "close": 415.0,
      "high": 418.5,
      "low": 403.4,
      "stop_hit": false,
      "stop_probable": false,
      "stop_status": "SAFE",
      "note": "Close \u20b9415.00 | Stop \u20b9477.12 | P&L +0.06R",
      "pnl_pct": 0.81,
      "pnl_r": 0.06,
      "exit_due": false,
      "day_number": 5,
      "fetch_time": "03:35 PM IST"
    },
    {
      "symbol": "ULTRACEMCO.NS",
      "signal": "DOWN_TRI",
      "signal_date": "2026-05-13",
      "direction": "SHORT",
      "entry": 11516.0,
      "stop": 12610.28,
      "open": 11540.0,
      "close": 11368.0,
      "high": 11556.0,
      "low": 11347.0,
      "stop_hit": false,
      "stop_probable": false,
      "stop_status": "SAFE",
      "note": "Close \u20b911368.00 | Stop \u20b912610.28 | P&L +0.14R",
      "pnl_pct": 1.29,
      "pnl_r": 0.14,
      "exit_due": false,
      "day_number": 5,
      "fetch_time": "03:35 PM IST"
    },
    {
      "symbol": "WHIRLPOOL.NS",
      "signal": "DOWN_TRI",
      "signal_date": "2026-05-13",
      "direction": "SHORT",
      "entry": 861.8,
      "stop": 1066.59,
      "open": 855.0,
      "close": 849.85,
      "high": 868.9,
      "low": 843.9,
      "stop_hit": false,
      "stop_probable": false,
      "stop_status": "SAFE",
      "note": "Close \u20b9849.85 | Stop \u20b91066.59 | P&L +0.06R",
      "pnl_pct": 1.39,
      "pnl_r": 0.06,
      "exit_due": false,
      "day_number": 5,
      "fetch_time": "03:35 PM IST"
    },
    {
      "symbol": "UNITDSPR.NS",
      "signal": "DOWN_TRI",
      "signal_date": "2026-05-13",
      "direction": "SHORT",
      "entry": 1247.5,
      "stop": 1449.58,
      "open": 1309.1,
      "close": 1304.9,
      "high": 1328.0,
      "low": 1300.4,
      "stop_hit": false,
      "stop_probable": false,
      "stop_status": "SAFE",
      "note": "Close \u20b91304.90 | Stop \u20b91449.58 | P&L -0.28R",
      "pnl_pct": -4.6,
      "pnl_r": -0.28,
      "exit_due": false,
      "day_number": 5,
      "fetch_time": "03:35 PM IST"
    },
    {
      "symbol": "AJANTPHARM.NS",
      "signal": "UP_TRI",
      "signal_date": "2026-05-13",
      "direction": "LONG",
      "entry": 3091.7,
      "stop": 2662.9,
      "open": 3249.1,
      "close": 3248.2,
      "high": 3314.9,
      "low": 3172.1,
      "stop_hit": false,
      "stop_probable": false,
      "stop_status": "SAFE",
      "note": "Close \u20b93248.20 | Stop \u20b92662.90 | P&L +0.36R",
      "pnl_pct": 5.06,
      "pnl_r": 0.36,
      "exit_due": false,
      "day_number": 5,
      "fetch_time": "03:35 PM IST"
    },
    {
      "symbol": "JSWENERGY.NS",
      "signal": "DOWN_TRI",
      "signal_date": "2026-05-13",
      "direction": "SHORT",
      "entry": 517.95,
      "stop": 605.4,
      "open": 534.9,
      "close": 533.15,
      "high": 539.5,
      "low": 528.55,
      "stop_hit": false,
      "stop_probable": false,
      "stop_status": "SAFE",
      "note": "Close \u20b9533.15 | Stop \u20b9605.40 | P&L -0.17R",
      "pnl_pct": -2.93,
      "pnl_r": -0.17,
      "exit_due": false,
      "day_number": 5,
      "fetch_time": "03:35 PM IST"
    },
    {
      "symbol": "HDFCLIFE.NS",
      "signal": "UP_TRI",
      "signal_date": "2026-05-15",
      "direction": "LONG",
      "entry": 612.55,
      "stop": 562.4,
      "open": 603.1,
      "close": 610.4,
      "high": 617.5,
      "low": 603.1,
      "stop_hit": false,
      "stop_probable": false,
      "stop_status": "SAFE",
      "note": "Close \u20b9610.40 | Stop \u20b9562.40 | P&L -0.04R",
      "pnl_pct": -0.35,
      "pnl_r": -0.04,
      "exit_due": false,
      "day_number": 3,
      "fetch_time": "03:35 PM IST"
    },
    {
      "symbol": "CHOLAFIN.NS",
      "signal": "UP_TRI",
      "signal_date": "2026-05-15",
      "direction": "LONG",
      "entry": 1567.1,
      "stop": 1416.35,
      "open": 1518.0,
      "close": 1511.4,
      "high": 1538.3,
      "low": 1508.0,
      "stop_hit": false,
      "stop_probable": false,
      "stop_status": "SAFE",
      "note": "Close \u20b91511.40 | Stop \u20b91416.35 | P&L -0.37R",
      "pnl_pct": -3.55,
      "pnl_r": -0.37,
      "exit_due": false,
      "day_number": 3,
      "fetch_time": "03:35 PM IST"
    },
    {
      "symbol": "ICICIGI.NS",
      "signal": "UP_TRI",
      "signal_date": "2026-05-15",
      "direction": "LONG",
      "entry": 1848.9,
      "stop": 1690.99,
      "open": 1813.0,
      "close": 1822.8,
      "high": 1833.2,
      "low": 1807.8,
      "stop_hit": false,
      "stop_probable": false,
      "stop_status": "SAFE",
      "note": "Close \u20b91822.80 | Stop \u20b91690.99 | P&L -0.17R",
      "pnl_pct": -1.41,
      "pnl_r": -0.17,
      "exit_due": false,
      "day_number": 3,
      "fetch_time": "03:35 PM IST"
    },
    {
      "symbol": "BAJAJ-AUTO.NS",
      "signal": "UP_TRI",
      "signal_date": "2026-05-15",
      "direction": "LONG",
      "entry": 10451.0,
      "stop": 9097.76,
      "open": 10198.5,
      "close": 10205.0,
      "high": 10285.0,
      "low": 10143.0,
      "stop_hit": false,
      "stop_probable": false,
      "stop_status": "SAFE",
      "note": "Close \u20b910205.00 | Stop \u20b99097.76 | P&L -0.18R",
      "pnl_pct": -2.35,
      "pnl_r": -0.18,
      "exit_due": false,
      "day_number": 3,
      "fetch_time": "03:35 PM IST"
    },
    {
      "symbol": "LAURUSLABS.NS",
      "signal": "UP_TRI",
      "signal_date": "2026-05-15",
      "direction": "LONG",
      "entry": 1315.5,
      "stop": 1048.02,
      "open": 1335.0,
      "close": 1344.9,
      "high": 1353.1,
      "low": 1322.1,
      "stop_hit": false,
      "stop_probable": false,
      "stop_status": "SAFE",
      "note": "Close \u20b91344.90 | Stop \u20b91048.02 | P&L +0.11R",
      "pnl_pct": 2.23,
      "pnl_r": 0.11,
      "exit_due": false,
      "day_number": 3,
      "fetch_time": "03:35 PM IST"
    },
    {
      "symbol": "VEDL.NS",
      "signal": "UP_TRI",
      "signal_date": "2026-05-15",
      "direction": "LONG",
      "entry": 338.9,
      "stop": 177.08,
      "open": 325.4,
      "close": 337.65,
      "high": 339.0,
      "low": 325.4,
      "stop_hit": false,
      "stop_probable": false,
      "stop_status": "SAFE",
      "note": "Close \u20b9337.65 | Stop \u20b9177.08 | P&L -0.01R",
      "pnl_pct": -0.37,
      "pnl_r": -0.01,
      "exit_due": false,
      "day_number": 3,
      "fetch_time": "03:35 PM IST"
    },
    {
      "symbol": "JINDALSTEL.NS",
      "signal": "UP_TRI",
      "signal_date": "2026-05-15",
      "direction": "LONG",
      "entry": 1252.8,
      "stop": 1163.46,
      "open": 1237.0,
      "close": 1226.3,
      "high": 1237.7,
      "low": 1221.2,
      "stop_hit": false,
      "stop_probable": false,
      "stop_status": "SAFE",
      "note": "Close \u20b91226.30 | Stop \u20b91163.46 | P&L -0.30R",
      "pnl_pct": -2.12,
      "pnl_r": -0.3,
      "exit_due": false,
      "day_number": 3,
      "fetch_time": "03:35 PM IST"
    },
    {
      "symbol": "SHREECEM.NS",
      "signal": "UP_TRI",
      "signal_date": "2026-05-15",
      "direction": "LONG",
      "entry": 25025.0,
      "stop": 23143.55,
      "open": 24450.0,
      "close": 24425.0,
      "high": 24585.0,
      "low": 24270.0,
      "stop_hit": false,
      "stop_probable": false,
      "stop_status": "SAFE",
      "note": "Close \u20b924425.00 | Stop \u20b923143.55 | P&L -0.32R",
      "pnl_pct": -2.4,
      "pnl_r": -0.32,
      "exit_due": false,
      "day_number": 3,
      "fetch_time": "03:35 PM IST"
    },
    {
      "symbol": "PHOENIXLTD.NS",
      "signal": "BULL_PROXY",
      "signal_date": "2026-05-15",
      "direction": "LONG",
      "entry": 1760.3,
      "stop": 1629.61,
      "open": 1710.0,
      "close": 1721.8,
      "high": 1754.0,
      "low": 1708.2,
      "stop_hit": false,
      "stop_probable": false,
      "stop_status": "SAFE",
      "note": "Close \u20b91721.80 | Stop \u20b91629.61 | P&L -0.29R",
      "pnl_pct": -2.19,
      "pnl_r": -0.29,
      "exit_due": false,
      "day_number": 3,
      "fetch_time": "03:35 PM IST"
    },
    {
      "symbol": "ASIANPAINT.NS",
      "signal": "UP_TRI",
      "signal_date": "2026-05-15",
      "direction": "LONG",
      "entry": 2622.2,
      "stop": 2324.64,
      "open": 2629.0,
      "close": 2600.7,
      "high": 2646.0,
      "low": 2595.1,
      "stop_hit": false,
      "stop_probable": false,
      "stop_status": "SAFE",
      "note": "Close \u20b92600.70 | Stop \u20b92324.64 | P&L -0.07R",
      "pnl_pct": -0.82,
      "pnl_r": -0.07,
      "exit_due": false,
      "day_number": 3,
      "fetch_time": "03:35 PM IST"
    },
    {
      "symbol": "BERGEPAINT.NS",
      "signal": "UP_TRI",
      "signal_date": "2026-05-15",
      "direction": "LONG",
      "entry": 533.9,
      "stop": 441.56,
      "open": 525.0,
      "close": 507.7,
      "high": 528.1,
      "low": 505.0,
      "stop_hit": false,
      "stop_probable": false,
      "stop_status": "SAFE",
      "note": "Close \u20b9507.70 | Stop \u20b9441.56 | P&L -0.28R",
      "pnl_pct": -4.91,
      "pnl_r": -0.28,
      "exit_due": false,
      "day_number": 3,
      "fetch_time": "03:35 PM IST"
    },
    {
      "symbol": "CYIENT.NS",
      "signal": "UP_TRI",
      "signal_date": "2026-05-15",
      "direction": "LONG",
      "entry": 871.85,
      "stop": 805.87,
      "open": 875.25,
      "close": 905.85,
      "high": 910.4,
      "low": 875.25,
      "stop_hit": false,
      "stop_probable": false,
      "stop_status": "SAFE",
      "note": "Close \u20b9905.85 | Stop \u20b9805.87 | P&L +0.52R",
      "pnl_pct": 3.9,
      "pnl_r": 0.52,
      "exit_due": false,
      "day_number": 3,
      "fetch_time": "03:35 PM IST"
    },
    {
      "symbol": "ENDURANCE.NS",
      "signal": "UP_TRI",
      "signal_date": "2026-05-15",
      "direction": "LONG",
      "entry": 2619.6,
      "stop": 2224.39,
      "open": 2509.0,
      "close": 2545.2,
      "high": 2569.0,
      "low": 2501.0,
      "stop_hit": false,
      "stop_probable": false,
      "stop_status": "SAFE",
      "note": "Close \u20b92545.20 | Stop \u20b92224.39 | P&L -0.19R",
      "pnl_pct": -2.84,
      "pnl_r": -0.19,
      "exit_due": false,
      "day_number": 3,
      "fetch_time": "03:35 PM IST"
    },
    {
      "symbol": "ZYDUSLIFE.NS",
      "signal": "UP_TRI",
      "signal_date": "2026-05-15",
      "direction": "LONG",
      "entry": 991.7,
      "stop": 866.38,
      "open": 995.0,
      "close": 1018.9,
      "high": 1048.0,
      "low": 995.0,
      "stop_hit": false,
      "stop_probable": false,
      "stop_status": "SAFE",
      "note": "Close \u20b91018.90 | Stop \u20b9866.38 | P&L +0.22R",
      "pnl_pct": 2.74,
      "pnl_r": 0.22,
      "exit_due": false,
      "day_number": 3,
      "fetch_time": "03:35 PM IST"
    },
    {
      "symbol": "JKCEMENT.NS",
      "signal": "UP_TRI",
      "signal_date": "2026-05-15",
      "direction": "LONG",
      "entry": 5521.5,
      "stop": 5025.07,
      "open": 5413.5,
      "close": 5434.5,
      "high": 5475.0,
      "low": 5380.5,
      "stop_hit": false,
      "stop_probable": false,
      "stop_status": "SAFE",
      "note": "Close \u20b95434.50 | Stop \u20b95025.07 | P&L -0.18R",
      "pnl_pct": -1.58,
      "pnl_r": -0.18,
      "exit_due": false,
      "day_number": 3,
      "fetch_time": "03:35 PM IST"
    },
    {
      "symbol": "THERMAX.NS",
      "signal": "UP_TRI",
      "signal_date": "2026-05-15",
      "direction": "LONG",
      "entry": 4597.7,
      "stop": 3760.26,
      "open": 4397.4,
      "close": 4416.6,
      "high": 4498.5,
      "low": 4335.1,
      "stop_hit": false,
      "stop_probable": false,
      "stop_status": "SAFE",
      "note": "Close \u20b94416.60 | Stop \u20b93760.26 | P&L -0.22R",
      "pnl_pct": -3.94,
      "pnl_r": -0.22,
      "exit_due": false,
      "day_number": 3,
      "fetch_time": "03:35 PM IST"
    },
    {
      "symbol": "MAXHEALTH.NS",
      "signal": "UP_TRI",
      "signal_date": "2026-05-15",
      "direction": "LONG",
      "entry": 1049.55,
      "stop": 905.49,
      "open": 1061.6,
      "close": 1068.75,
      "high": 1080.0,
      "low": 1054.65,
      "stop_hit": false,
      "stop_probable": false,
      "stop_status": "SAFE",
      "note": "Close \u20b91068.75 | Stop \u20b9905.49 | P&L +0.13R",
      "pnl_pct": 1.83,
      "pnl_r": 0.13,
      "exit_due": false,
      "day_number": 3,
      "fetch_time": "03:35 PM IST"
    },
    {
      "symbol": "LALPATHLAB.NS",
      "signal": "UP_TRI",
      "signal_date": "2026-05-15",
      "direction": "LONG",
      "entry": 1600.1,
      "stop": 1324.89,
      "open": 1659.8,
      "close": 1703.7,
      "high": 1719.9,
      "low": 1648.0,
      "stop_hit": false,
      "stop_probable": false,
      "stop_status": "SAFE",
      "note": "Close \u20b91703.70 | Stop \u20b91324.89 | P&L +0.38R",
      "pnl_pct": 6.47,
      "pnl_r": 0.38,
      "exit_due": false,
      "day_number": 3,
      "fetch_time": "03:35 PM IST"
    },
    {
      "symbol": "KOTAKBANK.NS",
      "signal": "UP_TRI",
      "signal_date": "2026-05-19",
      "direction": "LONG",
      "entry": 391.8,
      "stop": 353.36,
      "open": 388.5,
      "close": 381.95,
      "high": 391.8,
      "low": 380.25,
      "stop_hit": false,
      "stop_probable": false,
      "stop_status": "SAFE",
      "note": "Close \u20b9381.95 | Stop \u20b9353.36 | P&L -0.26R",
      "pnl_pct": -2.51,
      "pnl_r": -0.26,
      "exit_due": false,
      "day_number": 2,
      "fetch_time": "03:35 PM IST"
    },
    {
      "symbol": "INDUSINDBK.NS",
      "signal": "BULL_PROXY",
      "signal_date": "2026-05-19",
      "direction": "LONG",
      "entry": 892.15,
      "stop": 835.81,
      "open": 898.5,
      "close": 895.25,
      "high": 904.1,
      "low": 888.8,
      "stop_hit": false,
      "stop_probable": false,
      "stop_status": "SAFE",
      "note": "Close \u20b9895.25 | Stop \u20b9835.81 | P&L +0.06R",
      "pnl_pct": 0.35,
      "pnl_r": 0.06,
      "exit_due": false,
      "day_number": 2,
      "fetch_time": "03:35 PM IST"
    },
    {
      "symbol": "JINDALSTEL.NS",
      "signal": "BULL_PROXY",
      "signal_date": "2026-05-19",
      "direction": "LONG",
      "entry": 1231.8,
      "stop": 1180.95,
      "open": 1237.0,
      "close": 1226.3,
      "high": 1237.7,
      "low": 1221.2,
      "stop_hit": false,
      "stop_probable": false,
      "stop_status": "SAFE",
      "note": "Close \u20b91226.30 | Stop \u20b91180.95 | P&L -0.11R",
      "pnl_pct": -0.45,
      "pnl_r": -0.11,
      "exit_due": false,
      "day_number": 2,
      "fetch_time": "03:35 PM IST"
    },
    {
      "symbol": "NATIONALUM.NS",
      "signal": "UP_TRI",
      "signal_date": "2026-05-19",
      "direction": "LONG",
      "entry": 400.45,
      "stop": 373.46,
      "open": 402.0,
      "close": 398.95,
      "high": 403.5,
      "low": 391.45,
      "stop_hit": false,
      "stop_probable": false,
      "stop_status": "SAFE",
      "note": "Close \u20b9398.95 | Stop \u20b9373.46 | P&L -0.06R",
      "pnl_pct": -0.37,
      "pnl_r": -0.06,
      "exit_due": false,
      "day_number": 2,
      "fetch_time": "03:35 PM IST"
    },
    {
      "symbol": "NATIONALUM.NS",
      "signal": "BULL_PROXY",
      "signal_date": "2026-05-19",
      "direction": "LONG",
      "entry": 400.45,
      "stop": 380.87,
      "open": 402.0,
      "close": 398.95,
      "high": 403.5,
      "low": 391.45,
      "stop_hit": false,
      "stop_probable": false,
      "stop_status": "SAFE",
      "note": "Close \u20b9398.95 | Stop \u20b9380.87 | P&L -0.08R",
      "pnl_pct": -0.37,
      "pnl_r": -0.08,
      "exit_due": false,
      "day_number": 2,
      "fetch_time": "03:35 PM IST"
    },
    {
      "symbol": "HINDCOPPER.NS",
      "signal": "UP_TRI",
      "signal_date": "2026-05-19",
      "direction": "LONG",
      "entry": 581.15,
      "stop": 511.78,
      "open": 586.05,
      "close": 569.5,
      "high": 587.0,
      "low": 568.0,
      "stop_hit": false,
      "stop_probable": false,
      "stop_status": "SAFE",
      "note": "Close \u20b9569.50 | Stop \u20b9511.78 | P&L -0.17R",
      "pnl_pct": -2.0,
      "pnl_r": -0.17,
      "exit_due": false,
      "day_number": 2,
      "fetch_time": "03:35 PM IST"
    },
    {
      "symbol": "CAMS.NS",
      "signal": "UP_TRI",
      "signal_date": "2026-05-19",
      "direction": "LONG",
      "entry": 772.75,
      "stop": 693.99,
      "open": 771.95,
      "close": 779.35,
      "high": 786.7,
      "low": 770.15,
      "stop_hit": false,
      "stop_probable": false,
      "stop_status": "SAFE",
      "note": "Close \u20b9779.35 | Stop \u20b9693.99 | P&L +0.08R",
      "pnl_pct": 0.85,
      "pnl_r": 0.08,
      "exit_due": false,
      "day_number": 2,
      "fetch_time": "03:35 PM IST"
    },
    {
      "symbol": "APLAPOLLO.NS",
      "signal": "UP_TRI",
      "signal_date": "2026-05-19",
      "direction": "LONG",
      "entry": 1876.0,
      "stop": 1767.54,
      "open": 1882.0,
      "close": 1864.5,
      "high": 1888.9,
      "low": 1853.6,
      "stop_hit": false,
      "stop_probable": false,
      "stop_status": "SAFE",
      "note": "Close \u20b91864.50 | Stop \u20b91767.54 | P&L -0.11R",
      "pnl_pct": -0.61,
      "pnl_r": -0.11,
      "exit_due": false,
      "day_number": 2,
      "fetch_time": "03:35 PM IST"
    }
  ],
  "ohlc_by_symbol": {
    "COCHINSHIP.NS": {
      "2026-05-19": {
        "open": 1516.0,
        "high": 1531.0,
        "low": 1484.1,
        "close": 1489.6
      }
    },
    "GRSE.NS": {
      "2026-05-19": {
        "open": 2595.0,
        "high": 2685.0,
        "low": 2595.0,
        "close": 2658.5
      }
    },
    "YESBANK.NS": {
      "2026-05-19": {
        "open": 21.84,
        "high": 22.13,
        "low": 21.72,
        "close": 21.97
      }
    },
    "COLPAL.NS": {
      "2026-05-19": {
        "open": 2152.0,
        "high": 2223.7,
        "low": 2152.0,
        "close": 2188.3
      }
    },
    "NYKAA.NS": {
      "2026-05-19": {
        "open": 274.95,
        "high": 275.2,
        "low": 270.0,
        "close": 271.45
      }
    },
    "RVNL.NS": {
      "2026-05-19": {
        "open": 276.85,
        "high": 278.3,
        "low": 270.35,
        "close": 271.55
      }
    },
    "SUMICHEM.NS": {
      "2026-05-19": {
        "open": 453.95,
        "high": 474.8,
        "low": 450.05,
        "close": 468.9
      }
    },
    "GNFC.NS": {
      "2026-05-19": {
        "open": 532.9,
        "high": 552.0,
        "low": 526.0,
        "close": 545.95
      }
    },
    "AUBANK.NS": {
      "2026-05-19": {
        "open": 980.0,
        "high": 982.9,
        "low": 968.6,
        "close": 971.9
      }
    },
    "SBILIFE.NS": {
      "2026-05-19": {
        "open": 1846.0,
        "high": 1892.0,
        "low": 1845.4,
        "close": 1881.4
      }
    },
    "HINDUNILVR.NS": {
      "2026-05-19": {
        "open": 2242.0,
        "high": 2282.0,
        "low": 2229.5,
        "close": 2232.9
      }
    },
    "KEC.NS": {
      "2026-05-19": {
        "open": 490.4,
        "high": 495.0,
        "low": 466.0,
        "close": 469.4
      }
    },
    "FORTIS.NS": {
      "2026-05-19": {
        "open": 962.15,
        "high": 975.0,
        "low": 955.5,
        "close": 960.55
      }
    },
    "AARTIIND.NS": {
      "2026-05-19": {
        "open": 460.0,
        "high": 471.6,
        "low": 458.0,
        "close": 469.25
      }
    },
    "INFY.NS": {
      "2026-05-19": {
        "open": 1162.0,
        "high": 1198.4,
        "low": 1162.0,
        "close": 1196.9
      }
    },
    "COALINDIA.NS": {
      "2026-05-19": {
        "open": 462.1,
        "high": 463.25,
        "low": 454.0,
        "close": 456.95
      }
    },
    "BAJAJ-AUTO.NS": {
      "2026-05-19": {
        "open": 10198.5,
        "high": 10285.0,
        "low": 10143.0,
        "close": 10205.0
      }
    },
    "APLAPOLLO.NS": {
      "2026-05-19": {
        "open": 1882.0,
        "high": 1888.9,
        "low": 1853.6,
        "close": 1864.5
      }
    },
    "RBLBANK.NS": {
      "2026-05-19": {
        "open": 327.4,
        "high": 332.15,
        "low": 322.55,
        "close": 323.65
      }
    },
    "NATIONALUM.NS": {
      "2026-05-19": {
        "open": 402.0,
        "high": 403.5,
        "low": 391.45,
        "close": 398.95
      }
    },
    "POWERGRID.NS": {
      "2026-05-19": {
        "open": 296.6,
        "high": 300.0,
        "low": 294.55,
        "close": 298.6
      }
    },
    "NTPC.NS": {
      "2026-05-19": {
        "open": 386.7,
        "high": 392.75,
        "low": 386.05,
        "close": 389.4
      }
    },
    "AMBUJACEM.NS": {
      "2026-05-19": {
        "open": 430.5,
        "high": 434.6,
        "low": 428.8,
        "close": 431.7
      }
    },
    "ACC.NS": {
      "2026-05-19": {
        "open": 1367.5,
        "high": 1373.1,
        "low": 1353.3,
        "close": 1359.3
      }
    },
    "TORNTPOWER.NS": {
      "2026-05-19": {
        "open": 1533.5,
        "high": 1543.9,
        "low": 1475.0,
        "close": 1480.3
      }
    },
    "MARUTI.NS": {
      "2026-05-19": {
        "open": 13034.0,
        "high": 13104.0,
        "low": 12900.0,
        "close": 12956.0
      }
    },
    "JSWSTEEL.NS": {
      "2026-05-19": {
        "open": 1298.0,
        "high": 1299.7,
        "low": 1282.7,
        "close": 1285.2
      }
    },
    "TATAPOWER.NS": {
      "2026-05-19": {
        "open": 404.3,
        "high": 418.5,
        "low": 403.4,
        "close": 415.0
      }
    },
    "ULTRACEMCO.NS": {
      "2026-05-19": {
        "open": 11540.0,
        "high": 11556.0,
        "low": 11347.0,
        "close": 11368.0
      }
    },
    "WHIRLPOOL.NS": {
      "2026-05-19": {
        "open": 855.0,
        "high": 868.9,
        "low": 843.9,
        "close": 849.85
      }
    },
    "UNITDSPR.NS": {
      "2026-05-19": {
        "open": 1309.1,
        "high": 1328.0,
        "low": 1300.4,
        "close": 1304.9
      }
    },
    "AJANTPHARM.NS": {
      "2026-05-19": {
        "open": 3249.1,
        "high": 3314.9,
        "low": 3172.1,
        "close": 3248.2
      }
    },
    "JSWENERGY.NS": {
      "2026-05-19": {
        "open": 534.9,
        "high": 539.5,
        "low": 528.55,
        "close": 533.15
      }
    },
    "HDFCLIFE.NS": {
      "2026-05-19": {
        "open": 603.1,
        "high": 617.5,
        "low": 603.1,
        "close": 610.4
      }
    },
    "CHOLAFIN.NS": {
      "2026-05-19": {
        "open": 1518.0,
        "high": 1538.3,
        "low": 1508.0,
        "close": 1511.4
      }
    },
    "ICICIGI.NS": {
      "2026-05-19": {
        "open": 1813.0,
        "high": 1833.2,
        "low": 1807.8,
        "close": 1822.8
      }
    },
    "LAURUSLABS.NS": {
      "2026-05-19": {
        "open": 1335.0,
        "high": 1353.1,
        "low": 1322.1,
        "close": 1344.9
      }
    },
    "VEDL.NS": {
      "2026-05-19": {
        "open": 325.4,
        "high": 339.0,
        "low": 325.4,
        "close": 337.65
      }
    },
    "JINDALSTEL.NS": {
      "2026-05-19": {
        "open": 1237.0,
        "high": 1237.7,
        "low": 1221.2,
        "close": 1226.3
      }
    },
    "SHREECEM.NS": {
      "2026-05-19": {
        "open": 24450.0,
        "high": 24585.0,
        "low": 24270.0,
        "close": 24425.0
      }
    },
    "PHOENIXLTD.NS": {
      "2026-05-19": {
        "open": 1710.0,
        "high": 1754.0,
        "low": 1708.2,
        "close": 1721.8
      }
    },
    "ASIANPAINT.NS": {
      "2026-05-19": {
        "open": 2629.0,
        "high": 2646.0,
        "low": 2595.1,
        "close": 2600.7
      }
    },
    "BERGEPAINT.NS": {
      "2026-05-19": {
        "open": 525.0,
        "high": 528.1,
        "low": 505.0,
        "close": 507.7
      }
    },
    "CYIENT.NS": {
      "2026-05-19": {
        "open": 875.25,
        "high": 910.4,
        "low": 875.25,
        "close": 905.85
      }
    },
    "ENDURANCE.NS": {
      "2026-05-19": {
        "open": 2509.0,
        "high": 2569.0,
        "low": 2501.0,
        "close": 2545.2
      }
    },
    "ZYDUSLIFE.NS": {
      "2026-05-19": {
        "open": 995.0,
        "high": 1048.0,
        "low": 995.0,
        "close": 1018.9
      }
    },
    "JKCEMENT.NS": {
      "2026-05-19": {
        "open": 5413.5,
        "high": 5475.0,
        "low": 5380.5,
        "close": 5434.5
      }
    },
    "THERMAX.NS": {
      "2026-05-19": {
        "open": 4397.4,
        "high": 4498.5,
        "low": 4335.1,
        "close": 4416.6
      }
    },
    "MAXHEALTH.NS": {
      "2026-05-19": {
        "open": 1061.6,
        "high": 1080.0,
        "low": 1054.65,
        "close": 1068.75
      }
    },
    "LALPATHLAB.NS": {
      "2026-05-19": {
        "open": 1659.8,
        "high": 1719.9,
        "low": 1648.0,
        "close": 1703.7
      }
    },
    "KOTAKBANK.NS": {
      "2026-05-19": {
        "open": 388.5,
        "high": 391.8,
        "low": 380.25,
        "close": 381.95
      }
    },
    "INDUSINDBK.NS": {
      "2026-05-19": {
        "open": 898.5,
        "high": 904.1,
        "low": 888.8,
        "close": 895.25
      }
    },
    "HINDCOPPER.NS": {
      "2026-05-19": {
        "open": 586.05,
        "high": 587.0,
        "low": 568.0,
        "close": 569.5
      }
    },
    "CAMS.NS": {
      "2026-05-19": {
        "open": 771.95,
        "high": 786.7,
        "low": 770.15,
        "close": 779.35
      }
    }
  },
  "schema_version": 2
}